[
  { "app": "tmux", "category": "Prefix", "action": "Send prefix", "keys": ["Ctrl+B Ctrl+B"], "description": "Send the tmux prefix key through to the active pane.", "tags": ["prefix", "send", "tmux"], "sourceUrl": "https://github.com/tmux/tmux/wiki/Getting-Started" },
  { "app": "tmux", "category": "Help", "action": "Show key bindings", "keys": ["Ctrl+B ?"], "description": "List tmux key bindings.", "tags": ["help", "keys", "bindings"], "sourceUrl": "https://github.com/tmux/tmux/wiki/Getting-Started" },
  { "app": "tmux", "category": "Sessions", "action": "Detach client", "keys": ["Ctrl+B d"], "description": "Detach the current tmux client from the session.", "tags": ["session", "detach", "client"], "sourceUrl": "https://github.com/tmux/tmux/wiki/Getting-Started" },
  { "app": "tmux", "category": "Sessions", "action": "Rename session", "keys": ["Ctrl+B Dollar"], "description": "Rename the current tmux session.", "tags": ["session", "rename"], "sourceUrl": "https://man7.org/linux/man-pages/man1/tmux.1.html" },
  { "app": "tmux", "category": "Sessions", "action": "Choose session", "keys": ["Ctrl+B s"], "description": "Open the interactive session chooser.", "tags": ["session", "choose", "switch"], "sourceUrl": "https://github.com/tmux/tmux/wiki/Getting-Started" },
  { "app": "tmux", "category": "Sessions", "action": "Command prompt", "keys": ["Ctrl+B :"], "description": "Open the tmux command prompt.", "tags": ["command", "prompt", "tmux"], "sourceUrl": "https://github.com/tmux/tmux/wiki/Getting-Started" },
  { "app": "tmux", "category": "Windows", "action": "New window", "keys": ["Ctrl+B c"], "description": "Create a new tmux window.", "tags": ["window", "new"], "sourceUrl": "https://github.com/tmux/tmux/wiki/Getting-Started" },
  { "app": "tmux", "category": "Windows", "action": "Rename window", "keys": ["Ctrl+B Comma"], "description": "Rename the current window.", "tags": ["window", "rename"], "sourceUrl": "https://github.com/tmux/tmux/wiki/Getting-Started" },
  { "app": "tmux", "category": "Windows", "action": "Close window", "keys": ["Ctrl+B Ampersand"], "description": "Close the current window after confirmation.", "tags": ["window", "close"], "sourceUrl": "https://github.com/tmux/tmux/wiki/Getting-Started" },
  { "app": "tmux", "category": "Windows", "action": "Next window", "keys": ["Ctrl+B n"], "description": "Switch to the next window.", "tags": ["window", "next", "navigation"], "sourceUrl": "https://github.com/tmux/tmux/wiki/Getting-Started" },
  { "app": "tmux", "category": "Windows", "action": "Previous window", "keys": ["Ctrl+B p"], "description": "Switch to the previous window.", "tags": ["window", "previous", "navigation"], "sourceUrl": "https://github.com/tmux/tmux/wiki/Getting-Started" },
  { "app": "tmux", "category": "Windows", "action": "Last window", "keys": ["Ctrl+B l"], "description": "Switch back to the last active window.", "tags": ["window", "last", "navigation"], "sourceUrl": "https://github.com/tmux/tmux/wiki/Getting-Started" },
  { "app": "tmux", "category": "Windows", "action": "Choose window", "keys": ["Ctrl+B w"], "description": "Open the interactive window chooser.", "tags": ["window", "choose", "switch"], "sourceUrl": "https://github.com/tmux/tmux/wiki/Getting-Started" },
  { "app": "tmux", "category": "Panes", "action": "Split pane horizontally", "keys": ["Ctrl+B DoubleQuote"], "description": "Split the active pane into top and bottom panes.", "tags": ["pane", "split", "horizontal"], "sourceUrl": "https://github.com/tmux/tmux/wiki/Getting-Started" },
  { "app": "tmux", "category": "Panes", "action": "Split pane vertically", "keys": ["Ctrl+B Percent"], "description": "Split the active pane into left and right panes.", "tags": ["pane", "split", "vertical"], "sourceUrl": "https://github.com/tmux/tmux/wiki/Getting-Started" },
  { "app": "tmux", "category": "Panes", "action": "Close pane", "keys": ["Ctrl+B x"], "description": "Close the active pane after confirmation.", "tags": ["pane", "close"], "sourceUrl": "https://github.com/tmux/tmux/wiki/Getting-Started" },
  { "app": "tmux", "category": "Panes", "action": "Next pane", "keys": ["Ctrl+B o"], "description": "Move focus to the next pane.", "tags": ["pane", "next", "focus"], "sourceUrl": "https://github.com/tmux/tmux/wiki/Getting-Started" },
  { "app": "tmux", "category": "Panes", "action": "Last pane", "keys": ["Ctrl+B Semicolon"], "description": "Return focus to the previously active pane.", "tags": ["pane", "last", "focus"], "sourceUrl": "https://github.com/tmux/tmux/wiki/Getting-Started" },
  { "app": "tmux", "category": "Panes", "action": "Move pane focus", "keys": ["Ctrl+B Left", "Ctrl+B Right", "Ctrl+B Up", "Ctrl+B Down"], "description": "Move focus to an adjacent pane.", "tags": ["pane", "focus", "navigation"], "sourceUrl": "https://github.com/tmux/tmux/wiki/Getting-Started" },
  { "app": "tmux", "category": "Panes", "action": "Resize pane", "keys": ["Ctrl+B Ctrl+Left", "Ctrl+B Ctrl+Right", "Ctrl+B Ctrl+Up", "Ctrl+B Ctrl+Down"], "description": "Resize the active pane.", "tags": ["pane", "resize", "layout"], "sourceUrl": "https://man7.org/linux/man-pages/man1/tmux.1.html" },
  { "app": "tmux", "category": "Panes", "action": "Toggle pane zoom", "keys": ["Ctrl+B z"], "description": "Zoom or unzoom the active pane.", "tags": ["pane", "zoom", "layout"], "sourceUrl": "https://github.com/tmux/tmux/wiki/Getting-Started" },
  { "app": "tmux", "category": "Panes", "action": "Show pane numbers", "keys": ["Ctrl+B q"], "description": "Show pane numbers for quick selection.", "tags": ["pane", "numbers", "navigation"], "sourceUrl": "https://github.com/tmux/tmux/wiki/Getting-Started" },
  { "app": "tmux", "category": "Copy Mode", "action": "Enter copy mode", "keys": ["Ctrl+B LeftBracket"], "description": "Enter copy mode for scrollback navigation and selection.", "tags": ["copy", "mode", "scrollback"], "sourceUrl": "https://github.com/tmux/tmux/wiki/Getting-Started" },
  { "app": "tmux", "category": "Copy Mode", "action": "Paste buffer", "keys": ["Ctrl+B RightBracket"], "description": "Paste the most recent tmux buffer.", "tags": ["paste", "buffer", "copy"], "sourceUrl": "https://github.com/tmux/tmux/wiki/Getting-Started" },
  { "app": "tmux", "category": "Copy Mode", "action": "List paste buffers", "keys": ["Ctrl+B Hash"], "description": "List tmux paste buffers.", "tags": ["paste", "buffer", "list"], "sourceUrl": "https://man7.org/linux/man-pages/man1/tmux.1.html" }
]
